karelRobot/__init__.py
karelRobot/app.py
karelRobot/karel.py
karelRobot/settings.py
karelRobot/superkarel.py
karelRobot-0.9.1.data/data/Lib/site-packages/karelRobot/icons/edit.png
karelRobot-0.9.1.data/data/Lib/site-packages/karelRobot/icons/new.png
karelRobot-0.9.1.data/data/Lib/site-packages/karelRobot/icons/open.png
karelRobot-0.9.1.data/data/Lib/site-packages/karelRobot/icons/play.png
karelRobot-0.9.1.data/data/Lib/site-packages/karelRobot/icons/reload.png
karelRobot-0.9.1.data/data/Lib/site-packages/karelRobot/icons/reset.png
karelRobot-0.9.1.data/data/Lib/site-packages/karelRobot/icons/running.png
karelRobot-0.9.1.data/data/Lib/site-packages/karelRobot/icons/save.png
karelRobot-0.9.1.data/data/Lib/site-packages/karelRobot/icons/saveas.png
karelRobot-0.9.1.data/data/Lib/site-packages/karelRobot/icons/settings.png
karelRobot-0.9.1.data/data/Lib/site-packages/karelRobot/icons/stop.png
karelRobot-0.9.1.dist-info/LICENSE
karelRobot-0.9.1.dist-info/METADATA
karelRobot-0.9.1.dist-info/WHEEL
karelRobot-0.9.1.dist-info/top_level.txt
karelRobot-0.9.1.dist-info/RECORD
