Metadata-Version: 2.1
Name: karelRobot
Version: 0.9.1
Summary: karel for python
Home-page: https://github.com/hbynlsl/karelRobot
Author: hbynlsl
Author-email: hbynlsl@hotmail.com
License: MIT Licence
Keywords: karel robot
Platform: UNKNOWN
